xform/__init__.py
xform/binding.py
xform/fields.py
xform/form.py
xform/httputil.py
xform/messages.py
xform/schema.py
xform/utils.py
xform/validate.py
xform/adapters/__init__.py
xform/adapters/aiohttp.py
xform/adapters/flask.py
xform/adapters/sanic.py
xform/adapters/tornado.py
xargs-0.5.0.dist-info/LICENSE
xargs-0.5.0.dist-info/METADATA
xargs-0.5.0.dist-info/WHEEL
xargs-0.5.0.dist-info/top_level.txt
xargs-0.5.0.dist-info/RECORD
