Metadata-Version: 2.1
Name: xargs
Version: 0.5.0
Summary: Binding form data validation framework.
Home-page: https://github.com/marcohong/xform
Author: Maco
Author-email: macohong@hotmail.com
License: MIT License
Keywords: Form validation,Data Binding,Tornado web,aiohttp web,Sanic web
Classifier: Development Status :: 4 - Beta
Classifier: Intended Audience :: Developers
Classifier: License :: OSI Approved :: MIT License
Classifier: Topic :: Software Development
Classifier: Topic :: Software Development :: Libraries
Classifier: Programming Language :: Python :: 3
Classifier: Programming Language :: Python :: 3.6
Classifier: Programming Language :: Python :: 3.7
Classifier: Programming Language :: Python :: 3.8
Classifier: Programming Language :: Python :: 3.9
Classifier: Programming Language :: Python :: Implementation :: CPython
Classifier: Operating System :: OS Independent
Classifier: Framework :: AsyncIO
Requires-Python: >=3.6
License-File: LICENSE
